.gitignore
CHANGELOG.rst
LICENSE.txt
MANIFEST.in
README.rst
setup.py
.github/workflows/python-unittest-on-pr-and-push.yml
docs/Makefile
docs/conf.py
docs/index.rst
docs/make.bat
docs/_exts/autoformat.py
docs/_exts/formatref.py
docs/_exts/rtdmockup.py
docs/_static/beginner_guide_data.zip
docs/_static/example.pdf
docs/_static/example.svg
docs/api/aggregators.rst
docs/api/datasources.rst
docs/api/drawntabletesting.rst
docs/api/fifodict.rst
docs/api/jdbcconnectionwrapper.rst
docs/api/jythonmultiprocessing.rst
docs/api/parallel.rst
docs/api/pygrametl.rst
docs/api/steps.rst
docs/api/tables.rst
docs/examples/bulkloading.rst
docs/examples/database.rst
docs/examples/datasources.rst
docs/examples/dimensions.rst
docs/examples/facttables.rst
docs/examples/jython.rst
docs/examples/parallel.rst
docs/examples/testing.rst
docs/quickstart/beginner.rst
docs/quickstart/install.rst
pygrametl/FIFODict.py
pygrametl/JDBCConnectionWrapper.py
pygrametl/__init__.py
pygrametl/aggregators.py
pygrametl/datasources.py
pygrametl/jythonmultiprocessing.py
pygrametl/parallel.py
pygrametl/steps.py
pygrametl/tables.py
pygrametl.egg-info/PKG-INFO
pygrametl.egg-info/SOURCES.txt
pygrametl.egg-info/dependency_links.txt
pygrametl.egg-info/entry_points.txt
pygrametl.egg-info/top_level.txt
pygrametl/drawntabletesting/__init__.py
pygrametl/drawntabletesting/dttr.py
pygrametl/drawntabletesting/formattable.py
pygrametl/jythonsupport/Value.class
pygrametl/jythonsupport/Value.java
tests/__init__.py
tests/test_datasources.py
tests/test_init.py
tests/utilities.py
tests/drawntabletesting/__init__.py
tests/drawntabletesting/test_dtt.py
tests/drawntabletesting/test_dttr.py
tests/drawntabletesting/dttr/assert_disjoint.dtt
tests/drawntabletesting/dttr/assert_equal.dtt
tests/drawntabletesting/dttr/assert_subset.dtt
tests/drawntabletesting/dttr/config.py
tests/drawntabletesting/dttr/connection_in_config.dtt
tests/drawntabletesting/dttr/datasource_in_config.dtt
tests/drawntabletesting/dttr/read_dt_from_csv.dtt
tests/drawntabletesting/dttr/rows.csv
tests/tables/__init__.py
tests/tables/test_Dimension.py
tests/tables/test_FactTable.py